{"ongoing_trials": {}, "hyperparameters": {"space": [{"class_name": "Int", "config": {"name": "units1", "default": null, "conditions": [], "min_value": 32, "max_value": 128, "step": 32, "sampling": "linear"}}, {"class_name": "Boolean", "config": {"name": "second_layer", "default": false, "conditions": []}}, {"class_name": "Float", "config": {"name": "dropout1", "default": 0.1, "conditions": [], "min_value": 0.1, "max_value": 0.5, "step": 0.1, "sampling": "linear"}}, {"class_name": "Choice", "config": {"name": "learning_rate", "default": 0.001, "conditions": [], "values": [0.001, 0.0005, 0.0001], "ordered": true}}, {"class_name": "Int", "config": {"name": "units2", "default": null, "conditions": [], "min_value": 16, "max_value": 64, "step": 16, "sampling": "linear"}}, {"class_name": "Float", "config": {"name": "dropout2", "default": 0.1, "conditions": [], "min_value": 0.1, "max_value": 0.5, "step": 0.1, "sampling": "linear"}}], "values": {"units1": 32, "second_layer": false, "dropout1": 0.1, "learning_rate": 0.001, "units2": 16, "dropout2": 0.1}}, "start_order": ["00", "01", "02", "03", "04", "05", "06", "07", "08", "09"], "end_order": ["00", "01", "02", "03", "04", "05", "06", "07", "08", "09"], "run_times": {"00": 1, "01": 1, "02": 1, "03": 1, "04": 1, "05": 1, "06": 1, "07": 1, "08": 1, "09": 1}, "retry_queue": [], "seed": 3837, "seed_state": 3891, "tried_so_far": ["fbd975903e8edf6ebb6579808d586ddb", "060f0ab285ee381d55c92e5730d831b3", "1a74e7ddabfd40cbf995b9f5ecdc10c3", "b7696a9d3a05d83f9315e8090f598534", "14cdcb6eec508c6c9cef012b6b92128f", "5bc9bc0c06ce609f17b85a4baa47e5d3", "9124dfc11b0ecfc7dddd93c495f532bd", "d030f2991eef7d37e495dc85ab02b728", "2c4e8eb1a19f65efd95f1fe6c5dfe674", "387a2824c820769d55d80239fd0eabb5"], "id_to_hash": {"00": "060f0ab285ee381d55c92e5730d831b3", "01": "d030f2991eef7d37e495dc85ab02b728", "02": "5bc9bc0c06ce609f17b85a4baa47e5d3", "03": "9124dfc11b0ecfc7dddd93c495f532bd", "04": "387a2824c820769d55d80239fd0eabb5", "05": "2c4e8eb1a19f65efd95f1fe6c5dfe674", "06": "1a74e7ddabfd40cbf995b9f5ecdc10c3", "07": "fbd975903e8edf6ebb6579808d586ddb", "08": "b7696a9d3a05d83f9315e8090f598534", "09": "14cdcb6eec508c6c9cef012b6b92128f"}, "display": {"search_start": "2025-06-14T16:48:27.400944", "trial_start": {"00": "2025-06-14T16:48:27.400944", "01": "2025-06-14T16:48:45.765405", "02": "2025-06-14T16:50:00.495711", "03": "2025-06-14T16:50:48.037788", "04": "2025-06-14T16:52:00.082550", "05": "2025-06-14T16:52:39.085123", "06": "2025-06-14T16:52:59.627488", "07": "2025-06-14T16:53:24.934325", "08": "2025-06-14T16:53:52.187340", "09": "2025-06-14T16:54:53.785165"}, "trial_number": {"00": 1, "01": 2, "02": 3, "03": 4, "04": 5, "05": 6, "06": 7, "07": 8, "08": 9, "09": 10}}}